undataio/__init__.py
undataio/demo.py
undataio/undata.py
undataio-0.1.0.dist-info/METADATA
undataio-0.1.0.dist-info/WHEEL
undataio-0.1.0.dist-info/top_level.txt
undataio-0.1.0.dist-info/RECORD
