Metadata-Version: 2.1
Name: undataio
Version: 0.1.0
Summary: test pip upload
Home-page: 
Author: lily
Author-email: 1909017169@qq.com
License: MIT
Requires-Python: >=3.8
Requires-Dist: requests~=2.32.3
Requires-Dist: requests-toolbelt==1.0.0
